{"UAE": {"raw_dict1": {"2142098": {"name": "JinxFehu", "faction_id": 19449, "faction_name": "Simulation", "prize": 0, "prize_on_hand": 0, "prize_total": 0, "arrive_time": "06:58~07:14", "arrive_ts_left": 1659394709, "arrive_ts_right": 1659395654, "bs": "-"}, "856826": {"name": "payne1144", "faction_id": 41238, "faction_name": "The Mile High Club", "prize": 0, "prize_on_hand": 0, "prize_total": 1000000, "arrive_time": "07:15~07:17", "arrive_ts_left": 1659395757, "arrive_ts_right": 1659395835, "bs": "-"}, "2541479": {"name": "OGsamuraiX", "faction_id": 17001, "faction_name": "Trigger Happy Devils", "prize": 0, "prize_on_hand": 0, "prize_total": 99000000, "arrive_time": "07:39~07:56", "arrive_ts_left": 1659397192, "arrive_ts_right": 1659398208, "bs": "2.5m ~ 20.4m", "in_clothes": false}, "2782456": {"name": "Ferrousferos", "faction_id": 41832, "faction_name": "Flying Cadets", "prize": 0, "prize_on_hand": 0, "prize_total": 0, "arrive_time": "08:02~08:17", "arrive_ts_left": 1659398561, "arrive_ts_right": 1659399463, "bs": "-"}, "2048364": {"name": "DeadBox", "faction_id": 39909, "faction_name": "Silent Roses", "prize": 0, "prize_on_hand": 0, "prize_total": 0, "arrive_time": "08:01~08:41", "arrive_ts_left": 1659398476, "arrive_ts_right": 1659400896, "bs": "-"}}, "raw_dict2": {"1855129": {"name": "BitchyBritches", "faction_id": 13784, "faction_name": "WarBirds", "prize": 0, "prize_on_hand": 0, "prize_total": 1001000000, "timestamp": 1659377009.5677044, "bs": "2.94b", "in_clothes": false}, "2554520": {"name": "Inafiel", "faction_id": 8803, "faction_name": "Buttgrass Inc", "prize": 39177600, "prize_on_hand": 0, "prize_total": 55478885, "timestamp": 1659389643.643699, "bs": "819.25m", "in_clothes": false}, "715582": {"name": "Osman", "faction_id": 33458, "faction_name": "PLATA", "prize": 0, "prize_on_hand": 0, "prize_total": 50000000, "timestamp": 1659390844.5721405, "bs": "2.01b", "in_clothes": false}, "2744339": {"name": "Reedy1980", "faction_id": 46165, "faction_name": "Travel Crew", "prize": 0, "prize_on_hand": 0, "prize_total": 37009762, "timestamp": 1659392292.122826, "bs": "210.28k", "in_clothes": false}, "2369867": {"name": "monty094", "faction_id": 26312, "faction_name": "Dynamic Chaos", "prize": 0, "prize_on_hand": 0, "prize_total": 110659518, "timestamp": 1659392314.3551452, "bs": "35.0m ~ 54.86m", "in_clothes": false}, "1640111": {"name": "Jobby", "faction_id": 9036, "faction_name": "The Black Pearl", "prize": 0, "prize_on_hand": 0, "prize_total": 52534000, "timestamp": 1659396296.560932, "bs": "4.41b", "in_clothes": false}, "2660461": {"name": "pjisbest", "faction_id": 44562, "faction_name": "Vanguard Titans", "prize": 0, "prize_on_hand": 0, "prize_total": 48611200, "timestamp": 1659397413.1387994, "bs": "2.5m ~ 6.79m", "in_clothes": false}, "202551": {"name": "Elazar", "faction_id": 22781, "faction_name": "The Wolverines", "prize": 0, "prize_on_hand": 0, "prize_total": 33800000, "timestamp": 1659397417.3444617, "bs": "5.0b", "in_clothes": false}, "2657364": {"name": "CinnamonPond", "faction_id": 18597, "faction_name": "The Collective Resistance", "prize": 0, "prize_on_hand": 0, "prize_total": 33770000, "timestamp": 1659399104.8495972, "bs": "245.31k", "in_clothes": false}, "2450243": {"name": "Reezo", "faction_id": 12249, "faction_name": "Aurora Surrealis", "prize": 0, "prize_on_hand": 0, "prize_total": 25127000, "timestamp": 1659400186.2647967, "bs": "56.44m", "in_clothes": false}, "2573462": {"name": "AvatarPatrick", "faction_id": 21239, "faction_name": "Hacienda", "prize": 0, "prize_on_hand": 0, "prize_total": 25150000, "timestamp": 1659400197.9015422, "bs": "250.0m ~ 534.86m", "in_clothes": false}}, "raw_dict3": {"2437546": {"name": "Oyibo", "faction_id": 36140, "faction_name": "Princess Dale&#039;s Beavers", "prize": 0, "prize_on_hand": 0, "prize_total": 38080000, "arrive_time": "08:44~08:46", "arrive_ts_left": 1659401099, "arrive_ts_right": 1659401210, "timestamp": 1659389969.3166852, "bs": "35.0m ~ 257.18m", "in_clothes": false}, "2739763": {"name": "Limbo", "faction_id": 46088, "faction_name": "The Den Of Thieves", "prize": 0, "prize_on_hand": 0, "prize_total": 1000999999, "arrive_time": "08:46~09:03", "arrive_ts_left": 1659401167, "arrive_ts_right": 1659402186, "timestamp": 1659390851.450226, "bs": "250.0k ~ 716.23k", "in_clothes": false}, "2387171": {"name": "black-", "faction_id": 13851, "faction_name": "Nuclear Therapy", "prize": 0, "prize_on_hand": 0, "prize_total": 1000000000, "arrive_time": "08:46~09:03", "arrive_ts_left": 1659401188, "arrive_ts_right": 1659402194, "timestamp": 1659390852.294637, "bs": "250.0k ~ 942.28k", "in_clothes": false}, "2250368": {"name": "TheRoyalChode", "faction_id": 37131, "faction_name": "-StONeD rAiDeRs-", "prize": 0, "prize_on_hand": 0, "prize_total": 99999999, "arrive_time": "09:08~09:25", "arrive_ts_left": 1659402535, "arrive_ts_right": 1659403528, "timestamp": 1659392318.6219854, "bs": "933.99m", "in_clothes": false}, "2728306": {"name": "Alimony", "faction_id": 21040, "faction_name": "Merchant Soldier Sage", "prize": 0, "prize_on_hand": 0, "prize_total": 62750000, "arrive_time": "09:08~09:25", "arrive_ts_left": 1659402502, "arrive_ts_right": 1659403515, "timestamp": 1659392319.4975727, "bs": "10.84m", "in_clothes": false}, "2497903": {"name": "torn_assasin", "faction_id": 8400, "faction_name": "Lingering Insanity", "prize": 0, "prize_on_hand": 0, "prize_total": 103397200, "arrive_time": "09:52~10:08", "arrive_ts_left": 1659405179, "arrive_ts_right": 1659406127, "timestamp": 1659394905.7676232, "bs": "766.83m", "in_clothes": false}, "2750509": {"name": "MayhemB", "faction_id": 46805, "faction_name": "Hummingbirds", "prize": 0, "prize_on_hand": 1147000, "prize_total": 30060600, "arrive_time": "09:52~10:08", "arrive_ts_left": 1659405154, "arrive_ts_right": 1659406107, "timestamp": 1659394906.6412368, "bs": "434.81k", "in_clothes": false}, "1632988": {"name": "N3m", "faction_id": 2013, "faction_name": "Subversive  Alliance", "prize": 20108169, "prize_on_hand": 0, "prize_total": 135051645, "arrive_time": "10:31~10:32", "arrive_ts_left": 1659407477, "arrive_ts_right": 1659407563, "timestamp": 1659396300.7633805, "bs": "10.7b"}, "2629220": {"name": "Adz93", "faction_id": 42435, "faction_name": "Nub Army", "prize": 0, "prize_on_hand": 0, "prize_total": 43471239, "arrive_time": "10:14~10:30", "arrive_ts_left": 1659406448, "arrive_ts_right": 1659407407, "timestamp": 1659396301.6389937, "bs": "2.5m ~ 8.13m", "in_clothes": false}, "1898281": {"name": "r11ley", "faction_id": 38887, "faction_name": "Medics", "prize": 0, "prize_on_hand": 0, "prize_total": 1680000000, "arrive_time": "10:32~10:35", "arrive_ts_left": 1659407554, "arrive_ts_right": 1659407746, "timestamp": 1659396572.1101155, "bs": "11.44m", "in_clothes": false}, "2741247": {"name": "Ansidinc", "faction_id": 23188, "faction_name": "Reign of Confusion", "prize": 0, "prize_on_hand": 0, "prize_total": 1000180000, "arrive_time": "10:35~10:52", "arrive_ts_left": 1659407752, "arrive_ts_right": 1659408734, "timestamp": 1659397412.280794, "bs": "1.04m"}, "1521645": {"name": "Pangtosh", "faction_id": 231, "faction_name": "Destructive Anomaly", "prize": 0, "prize_on_hand": 0, "prize_total": 20599996, "arrive_time": "10:36~10:51", "arrive_ts_left": 1659407795, "arrive_ts_right": 1659408707, "timestamp": 1659397418.9980783, "bs": "4.33b"}, "2767979": {"name": "_S_a_m_i_", "faction_id": 8317, "faction_name": "Naughty Souls", "prize": 0, "prize_on_hand": 0, "prize_total": 100000000, "arrive_time": "10:35~10:52", "arrive_ts_left": 1659407741, "arrive_ts_right": 1659408736, "timestamp": 1659397420.2480934, "bs": "25.0k ~ 54.94k", "in_clothes": false}, "2670339": {"name": "QPayne", "faction_id": 8938, "faction_name": "Arcadia", "prize": 0, "prize_on_hand": 0, "prize_total": 217108650, "arrive_time": "10:35~10:53", "arrive_ts_left": 1659407726, "arrive_ts_right": 1659408782, "timestamp": 1659397688.8879452, "bs": "66.3m"}, "2446126": {"name": "BOSS-BABY", "faction_id": 13851, "faction_name": "Nuclear Therapy", "prize": 5268200, "prize_on_hand": 0, "prize_total": 24341056, "arrive_time": "10:58~11:13", "arrive_ts_left": 1659409089, "arrive_ts_right": 1659410031, "timestamp": 1659398831.223831, "bs": "32.74m", "in_clothes": false}, "2333541": {"name": "stinkych33s3", "faction_id": 8468, "faction_name": "Bloodbath and Beyond", "prize": 0, "prize_on_hand": 0, "prize_total": 101206360, "arrive_time": "11:18~11:35", "arrive_ts_left": 1659410295, "arrive_ts_right": 1659411348, "timestamp": 1659400183.0627532, "bs": "529.0m"}, "2286533": {"name": "Kennedy", "faction_id": 37803, "faction_name": "The  Scullions", "prize": 0, "prize_on_hand": 0, "prize_total": 49500000, "arrive_time": "11:19~11:35", "arrive_ts_left": 1659410393, "arrive_ts_right": 1659411309, "timestamp": 1659400192.70207, "bs": "1.19b"}, "2284449": {"name": "A2gis", "faction_id": 16443, "faction_name": "Vietgang", "prize": 0, "prize_on_hand": 0, "prize_total": 334633333, "arrive_time": "11:19~11:35", "arrive_ts_left": 1659410362, "arrive_ts_right": 1659411316, "timestamp": 1659400201.119274, "bs": "196.69m", "in_clothes": false}}}, "United Kingdom": {"raw_dict1": {}, "raw_dict2": {"387023": {"name": "theSilence", "faction_id": 22680, "faction_name": "39th Street Chillers", "prize": 0, "prize_on_hand": 0, "prize_total": 39999999, "timestamp": 1659374581.3452778, "bs": "4.48b", "in_clothes": false}, "2037571": {"name": "Embezzle", "faction_id": 7818, "faction_name": "The Box", "prize": 0, "prize_on_hand": 0, "prize_total": 100000000, "timestamp": 1659379573.7242694, "bs": "1.69b", "in_clothes": false}, "2611083": {"name": "BazingaKhan", "faction_id": 41028, "faction_name": "Lightside", "prize": 0, "prize_on_hand": 0, "prize_total": 100000000, "timestamp": 1659389584.2045429, "bs": "2.5m ~ 3.27m", "in_clothes": true}, "2256264": {"name": "The_Hulk", "faction_id": 26312, "faction_name": "Dynamic Chaos", "prize": 870000, "prize_on_hand": 0, "prize_total": 64752600, "timestamp": 1659389590.997867, "bs": "250.0m ~ 404.74m", "in_clothes": false}}, "raw_dict3": {"2199030": {"name": "Lordraaj", "faction_id": 15929, "faction_name": "The Inquisition", "prize": 0, "prize_on_hand": 0, "prize_total": 4501435000, "arrive_time": "08:31~08:32", "arrive_ts_left": 1659400276, "arrive_ts_right": 1659400359, "timestamp": 1659393772.4583619, "bs": "760.38k", "in_clothes": false}, "2205470": {"name": "TheOA", "faction_id": 12094, "faction_name": "Nuclear Fusion", "prize": 91742200, "prize_on_hand": 3121244850, "prize_total": 3121244850, "arrive_time": "08:34~08:49", "arrive_ts_left": 1659400455, "arrive_ts_right": 1659401393, "timestamp": 1659394875.531642, "bs": "2.0b"}, "2549019": {"name": "Virgil", "faction_id": 9041, "faction_name": "PT-Calculated", "prize": 0, "prize_on_hand": 0, "prize_total": 1000000000, "arrive_time": "08:34~08:50", "arrive_ts_left": 1659400452, "arrive_ts_right": 1659401417, "timestamp": 1659394909.7108748, "bs": "1.01b", "in_clothes": false}, "2387057": {"name": "nokkies", "faction_id": 26885, "faction_name": "The Iron Prophecy", "prize": 0, "prize_on_hand": 0, "prize_total": 104254499, "arrive_time": "08:34~08:50", "arrive_ts_left": 1659400445, "arrive_ts_right": 1659401408, "timestamp": 1659394910.5688858, "bs": "35.0m ~ 354.33m", "in_clothes": false}, "2187512": {"name": "Bangers", "faction_id": 8819, "faction_name": "Violent if Necessary", "prize": 5382000, "prize_on_hand": 2044471, "prize_total": 26090358, "arrive_time": "08:34~08:50", "arrive_ts_left": 1659400470, "arrive_ts_right": 1659401421, "timestamp": 1659394911.4288974, "bs": "2.59b", "in_clothes": false}, "177901": {"name": "Gus", "faction_id": 2013, "faction_name": "Subversive  Alliance", "prize": 0, "prize_on_hand": 0, "prize_total": 2133144825, "arrive_time": "08:34~08:49", "arrive_ts_left": 1659400446, "arrive_ts_right": 1659401359, "timestamp": 1659394912.2889454, "bs": "10.08b", "in_clothes": false}, "2334640": {"name": "Piterson", "faction_id": 12249, "faction_name": "Aurora Surrealis", "prize": 0, "prize_on_hand": 0, "prize_total": 6979997176, "arrive_time": "09:12~09:14", "arrive_ts_left": 1659402761, "arrive_ts_right": 1659402848, "timestamp": 1659396304.607029, "bs": "250.0m ~ 568.79m", "in_clothes": false}, "2397221": {"name": "GenesisNara", "faction_id": 8510, "faction_name": "Ara Pacis", "prize": 0, "prize_on_hand": 0, "prize_total": 1003500000, "arrive_time": "08:55~09:11", "arrive_ts_left": 1659401736, "arrive_ts_right": 1659402695, "timestamp": 1659396305.8396652, "bs": "35.0m ~ 313.49m", "in_clothes": false}, "796044": {"name": "LearDriver", "faction_id": 9517, "faction_name": "OverWatch", "prize": 0, "prize_on_hand": 0, "prize_total": 54787500, "arrive_time": "09:17~09:33", "arrive_ts_left": 1659403066, "arrive_ts_right": 1659404005, "timestamp": 1659397377.2431476, "bs": "1.45b", "in_clothes": false}, "582646": {"name": "Kiminori", "faction_id": 27902, "faction_name": "SMTH - Concord", "prize": 0, "prize_on_hand": 0, "prize_total": 27217247, "arrive_time": "09:17~09:32", "arrive_ts_left": 1659403068, "arrive_ts_right": 1659403970, "timestamp": 1659397378.1051579, "bs": "7.5b", "in_clothes": false}, "175186": {"name": "Nadori", "faction_id": 7709, "faction_name": "Vulpes Vulpes", "prize": 0, "prize_on_hand": 0, "prize_total": 55489998, "arrive_time": "09:39~09:56", "arrive_ts_left": 1659404366, "arrive_ts_right": 1659405365, "timestamp": 1659398935.578072, "bs": "2.11b", "in_clothes": false}, "2664981": {"name": "Einhalden", "faction_id": 16282, "faction_name": "Nuclear Winter", "prize": 0, "prize_on_hand": 0, "prize_total": 19999999998, "arrive_time": "09:56~10:00", "arrive_ts_left": 1659405416, "arrive_ts_right": 1659405649, "timestamp": 1659399188.620871, "bs": "279.46m", "in_clothes": false}, "2542182": {"name": "Unforgiven_ve", "faction_id": 39010, "faction_name": "SCALLYWAGS", "prize": 0, "prize_on_hand": 0, "prize_total": 65800200, "arrive_time": "09:59~10:16", "arrive_ts_left": 1659405583, "arrive_ts_right": 1659406596, "timestamp": 1659399974.2643836, "bs": "915.88m", "in_clothes": false}, "2262435": {"name": "Wallyllama", "faction_id": 478, "faction_name": "PT-Penguins", "prize": 0, "prize_on_hand": 0, "prize_total": 45313175, "arrive_time": "10:00~10:15", "arrive_ts_left": 1659405622, "arrive_ts_right": 1659406537, "timestamp": 1659399975.202393, "bs": "1.85b", "in_clothes": false}, "1780663": {"name": "KingKush420", "faction_id": 8510, "faction_name": "Ara Pacis", "prize": 0, "prize_on_hand": 17673840, "prize_total": 55743500, "arrive_time": "10:00~10:15", "arrive_ts_left": 1659405651, "arrive_ts_right": 1659406526, "timestamp": 1659399976.1384056, "bs": "484.5m", "in_clothes": false}, "2650611": {"name": "No_Vitae", "faction_id": 8273, "faction_name": "Pandamonium", "prize": 9385810, "prize_on_hand": 16565899, "prize_total": 25951709, "arrive_time": "09:59~10:17", "arrive_ts_left": 1659405588, "arrive_ts_right": 1659406630, "timestamp": 1659399977.1232152, "bs": "150.38m", "in_clothes": false}}}, "Switzerland": {"raw_dict1": {}, "raw_dict2": {"1459388": {"name": "sa69", "faction_id": 9032, "faction_name": "Wolf Pack", "prize": 0, "prize_on_hand": 0, "prize_total": 400397996, "timestamp": 1659381063.5331059, "bs": "6.05b", "in_clothes": false}, "1375849": {"name": "LadyAlissa", "faction_id": 13737, "faction_name": "The War Rig", "prize": 0, "prize_on_hand": 0, "prize_total": 1000000000, "timestamp": 1659382093.5257387, "bs": "113.68m", "in_clothes": false}, "2112856": {"name": "ISHAAN", "faction_id": 11581, "faction_name": "Natural Selection III", "prize": 0, "prize_on_hand": 0, "prize_total": 10000000000, "timestamp": 1659383080.4029112, "bs": "2.2b", "in_clothes": false}, "422844": {"name": "Grefal", "faction_id": 41768, "faction_name": "Aces Elite", "prize": 0, "prize_on_hand": 0, "prize_total": 82550000, "timestamp": 1659383081.2161553, "bs": "2.21b", "in_clothes": false}, "1878591": {"name": "LycanNinety", "faction_id": 2095, "faction_name": "insurreXtion", "prize": 0, "prize_on_hand": 0, "prize_total": 22351000, "timestamp": 1659383093.796154, "bs": "2.26b", "in_clothes": false}, "1654906": {"name": "Mr-13", "faction_id": 231, "faction_name": "Destructive Anomaly", "prize": 0, "prize_on_hand": 0, "prize_total": 3050051000, "timestamp": 1659385678.1751642, "bs": "3.43b", "in_clothes": false}, "2148873": {"name": "3ball", "faction_id": 8819, "faction_name": "Violent if Necessary", "prize": 0, "prize_on_hand": 0, "prize_total": 25337500, "timestamp": 1659390891.6879342, "bs": "960.34m", "in_clothes": false}, "764144": {"name": "Kelesen", "faction_id": 8537, "faction_name": "NNGO", "prize": 0, "prize_on_hand": 0, "prize_total": 951067775, "timestamp": 1659391200.4772758, "bs": "35.0m ~ 80.08m", "in_clothes": false}, "1071220": {"name": "pat2008", "faction_id": 20747, "faction_name": "Damage Inc", "prize": 0, "prize_on_hand": 0, "prize_total": 304720000, "timestamp": 1659393595.8596854, "bs": "3.59b", "in_clothes": false}}, "raw_dict3": {"2102067": {"name": "Lilith137", "faction_id": 7835, "faction_name": "Monarch Engineering", "prize": 0, "prize_on_hand": 0, "prize_total": 27000000, "arrive_time": "08:24~08:40", "arrive_ts_left": 1659399868, "arrive_ts_right": 1659400831, "timestamp": 1659393591.6084306, "bs": "3.57b"}, "2132918": {"name": "Jtb083", "faction_id": 32585, "faction_name": "Heart of a Pirate", "prize": 0, "prize_on_hand": 1818000, "prize_total": 23479999, "arrive_time": "08:40~08:42", "arrive_ts_left": 1659400855, "arrive_ts_right": 1659400946, "timestamp": 1659393603.2233799, "bs": "1.89b"}, "2307915": {"name": "Klaus_Klausing", "faction_id": 8151, "faction_name": "LONDON", "prize": 7864800, "prize_on_hand": 10509600, "prize_total": 140164601, "arrive_time": "08:39~08:41", "arrive_ts_left": 1659400796, "arrive_ts_right": 1659400886, "timestamp": 1659393607.5770373, "bs": "782.83m"}, "1892442": {"name": "DeadCold", "faction_id": 20881, "faction_name": "Amoeba-", "prize": 0, "prize_on_hand": 0, "prize_total": 999999999, "arrive_time": "08:23~08:39", "arrive_ts_left": 1659399809, "arrive_ts_right": 1659400760, "timestamp": 1659393611.0442874, "bs": "250.0m ~ 524.46m", "in_clothes": false}, "431996": {"name": "iMac", "faction_id": 8422, "faction_name": "MMCP", "prize": 0, "prize_on_hand": 0, "prize_total": 10816499998, "arrive_time": "08:44~08:45", "arrive_ts_left": 1659401063, "arrive_ts_right": 1659401154, "timestamp": 1659393892.189961, "bs": "6.41b", "in_clothes": false}, "2315090": {"name": "h4xnoodle", "faction_id": 33241, "faction_name": "Nub Navy", "prize": 0, "prize_on_hand": 0, "prize_total": 300666674, "arrive_time": "08:45~09:01", "arrive_ts_left": 1659401112, "arrive_ts_right": 1659402079, "timestamp": 1659394735.408422, "bs": "1.08b", "in_clothes": false}, "2548492": {"name": "Ez4Ence", "faction_id": 11796, "faction_name": "Trinity", "prize": 0, "prize_on_hand": 0, "prize_total": 5465959000, "arrive_time": "08:46~09:01", "arrive_ts_left": 1659401196, "arrive_ts_right": 1659402090, "timestamp": 1659394736.2819996, "bs": "785.2m", "in_clothes": false}, "1852855": {"name": "WhiteMafia", "faction_id": 7835, "faction_name": "Monarch Engineering", "prize": 0, "prize_on_hand": 1360245, "prize_total": 209613182, "arrive_time": "08:46~09:01", "arrive_ts_left": 1659401189, "arrive_ts_right": 1659402097, "timestamp": 1659394737.3468144, "bs": "2.76b", "in_clothes": false}, "2387102": {"name": "aCreature", "faction_id": 8400, "faction_name": "Lingering Insanity", "prize": 22952500, "prize_on_hand": 0, "prize_total": 1384842207, "arrive_time": "08:45~09:01", "arrive_ts_left": 1659401159, "arrive_ts_right": 1659402107, "timestamp": 1659395017.7018774, "bs": "2.2b"}, "1686568": {"name": "Coce", "faction_id": 525, "faction_name": "EQ: Ministry of Mayhem", "prize": 0, "prize_on_hand": 0, "prize_total": 1014999999, "arrive_time": "08:45~09:02", "arrive_ts_left": 1659401159, "arrive_ts_right": 1659402143, "timestamp": 1659395019.4042616, "bs": "250.0m ~ 812.0m"}, "2257611": {"name": "BritishBenji", "faction_id": 9420, "faction_name": "Sacrifice", "prize": 0, "prize_on_hand": 83578700, "prize_total": 84105300, "arrive_time": "09:01~09:03", "arrive_ts_left": 1659402100, "arrive_ts_right": 1659402191, "timestamp": 1659395036.8753111, "bs": "1.81m ~ 2.0m"}, "2104164": {"name": "ACE007", "faction_id": 27312, "faction_name": "SA One  Punch", "prize": 0, "prize_on_hand": 0, "prize_total": 1705520542, "arrive_time": "08:46~09:02", "arrive_ts_left": 1659401166, "arrive_ts_right": 1659402145, "timestamp": 1659395041.8923779, "bs": "4.65m", "in_clothes": false}, "524358": {"name": "CDV", "faction_id": 946, "faction_name": "PT-IronHearts", "prize": 0, "prize_on_hand": 0, "prize_total": 100000000, "arrive_time": "08:46~09:01", "arrive_ts_left": 1659401172, "arrive_ts_right": 1659402097, "timestamp": 1659395042.7659874, "bs": "1.44b", "in_clothes": false}, "1850792": {"name": "Bigpinkbaby", "faction_id": 12863, "faction_name": "Destination Unknown", "prize": 0, "prize_on_hand": 0, "prize_total": 46370000, "arrive_time": "09:03~09:04", "arrive_ts_left": 1659402211, "arrive_ts_right": 1659402298, "timestamp": 1659395043.6591682, "bs": "250.0m ~ 2.17b", "in_clothes": false}, "2248136": {"name": "ReyDelPerreo", "faction_id": 8062, "faction_name": "Stygian: Awakening", "prize": 70970, "prize_on_hand": 14910930, "prize_total": 25243572, "arrive_time": "08:45~09:01", "arrive_ts_left": 1659401122, "arrive_ts_right": 1659402105, "timestamp": 1659395044.486009, "bs": "1.12b", "in_clothes": false}, "2691982": {"name": "Malignant", "faction_id": 33241, "faction_name": "Nub Navy", "prize": 34564000, "prize_on_hand": 4789600, "prize_total": 38864700, "arrive_time": "09:07~09:23", "arrive_ts_left": 1659402433, "arrive_ts_right": 1659403421, "timestamp": 1659396192.8253214, "bs": "18.13m"}, "922212": {"name": "Bullzeye", "faction_id": 21665, "faction_name": "Swiss Army of Light", "prize": 0, "prize_on_hand": 0, "prize_total": 12034126960, "arrive_time": "09:07~09:24", "arrive_ts_left": 1659402428, "arrive_ts_right": 1659403441, "timestamp": 1659396198.6846693, "bs": "21.2b"}, "2124236": {"name": "FawkedUp", "faction_id": 8062, "faction_name": "Stygian: Awakening", "prize": 0, "prize_on_hand": 2745745, "prize_total": 28498051, "arrive_time": "09:07~09:23", "arrive_ts_left": 1659402459, "arrive_ts_right": 1659403416, "timestamp": 1659396209.1724005, "bs": "2.09b"}, "2515051": {"name": "4-20", "faction_id": 36691, "faction_name": "Rabid Chihuahuas", "prize": 0, "prize_on_hand": 0, "prize_total": 26300000, "arrive_time": "09:07~09:24", "arrive_ts_left": 1659402470, "arrive_ts_right": 1659403448, "timestamp": 1659396214.303288, "bs": "1.19b"}, "1903685": {"name": "RhinoLikesFeet", "faction_id": 21665, "faction_name": "Swiss Army of Light", "prize": 0, "prize_on_hand": 0, "prize_total": 406399999, "arrive_time": "09:07~09:24", "arrive_ts_left": 1659402428, "arrive_ts_right": 1659403441, "timestamp": 1659396215.2120757, "bs": "6.1b", "in_clothes": false}, "1462458": {"name": "WillieD", "faction_id": 8062, "faction_name": "Stygian: Awakening", "prize": 0, "prize_on_hand": 0, "prize_total": 25000000, "arrive_time": "09:27~09:29", "arrive_ts_left": 1659403678, "arrive_ts_right": 1659403799, "timestamp": 1659396488.3738492, "bs": "1.49b", "in_clothes": false}, "844653": {"name": "Shanks", "faction_id": 8520, "faction_name": "Carbon X", "prize": 0, "prize_on_hand": 0, "prize_total": 553514999, "arrive_time": "09:26~09:44", "arrive_ts_left": 1659403616, "arrive_ts_right": 1659404687, "timestamp": 1659397325.2792945, "bs": "1.75b", "in_clothes": false}, "2341376": {"name": "Hellrazer_1", "faction_id": 18736, "faction_name": "Monarch Research", "prize": 0, "prize_on_hand": 0, "prize_total": 680925000, "arrive_time": "09:29~09:44", "arrive_ts_left": 1659403740, "arrive_ts_right": 1659404697, "timestamp": 1659397596.3857806, "bs": "1.59b", "in_clothes": false}}}, "South Africa": {"raw_dict1": {"1888329": {"name": "SeanIlI", "faction_id": 31312, "faction_name": "TORNado", "prize": 0, "prize_on_hand": 0, "prize_total": 0, "arrive_time": "06:54~07:11", "arrive_ts_left": 1659394487, "arrive_ts_right": 1659395490, "bs": "-"}, "2375134": {"name": "Kilroy228", "faction_id": 15446, "faction_name": "Druggies in Snuggies", "prize": 7577900, "prize_on_hand": 0, "prize_total": 7824900, "arrive_time": "07:15~07:31", "arrive_ts_left": 1659395747, "arrive_ts_right": 1659396694, "bs": "-"}, "2791937": {"name": "Skulloid", "faction_id": 9305, "faction_name": "Legitimate Business", "prize": 0, "prize_on_hand": 0, "prize_total": 0, "arrive_time": "07:15~07:32", "arrive_ts_left": 1659395730, "arrive_ts_right": 1659396732, "bs": "-"}, "2183909": {"name": "SaintVoid", "faction_id": 10741, "faction_name": "SMTH - Trisolary", "prize": 0, "prize_on_hand": 0, "prize_total": 0, "arrive_time": "07:16~07:32", "arrive_ts_left": 1659395790, "arrive_ts_right": 1659396737, "bs": "-"}, "2664660": {"name": "AssAssInMouth", "faction_id": 20211, "faction_name": "Royal Beasts", "prize": 0, "prize_on_hand": 0, "prize_total": 0, "arrive_time": "07:16~07:34", "arrive_ts_left": 1659395815, "arrive_ts_right": 1659396870, "bs": "-"}, "2765473": {"name": "Oddinn", "faction_id": 8152, "faction_name": "The Unwoke", "prize": 0, "prize_on_hand": 0, "prize_total": 0, "arrive_time": "07:32~07:35", "arrive_ts_left": 1659396776, "arrive_ts_right": 1659396931, "bs": "-"}, "2787297": {"name": "MsCarriage", "faction_id": 12894, "faction_name": "New Sith Order", "prize": 0, "prize_on_hand": 0, "prize_total": 0, "arrive_time": "07:37~07:52", "arrive_ts_left": 1659397034, "arrive_ts_right": 1659397921, "bs": "-"}, "2669423": {"name": "Warmaster-Horus", "faction_id": 42830, "faction_name": "SAS", "prize": 0, "prize_on_hand": 0, "prize_total": 0, "arrive_time": "07:36~07:52", "arrive_ts_left": 1659396968, "arrive_ts_right": 1659397946, "bs": "-"}, "2785324": {"name": "StepBot", "faction_id": 9305, "faction_name": "Legitimate Business", "prize": 0, "prize_on_hand": 0, "prize_total": 0, "arrive_time": "07:37~07:52", "arrive_ts_left": 1659397051, "arrive_ts_right": 1659397956, "bs": "-"}, "2227730": {"name": "Delukii", "faction_id": 15602, "faction_name": "Lone Wolves", "prize": 0, "prize_on_hand": 0, "prize_total": 0, "arrive_time": "07:36~07:52", "arrive_ts_left": 1659396996, "arrive_ts_right": 1659397931, "bs": "-"}, "2326006": {"name": "Bozzmann", "faction_id": 13726, "faction_name": "Dark Energy", "prize": 0, "prize_on_hand": 0, "prize_total": 0, "arrive_time": "07:54~07:55", "arrive_ts_left": 1659398057, "arrive_ts_right": 1659398144, "bs": "-"}, "2735450": {"name": "SlimJan", "faction_id": 37426, "faction_name": "REKmebabyonemoretime", "prize": 540000, "prize_on_hand": 0, "prize_total": 4540000, "arrive_time": "08:13~08:15", "arrive_ts_left": 1659399220, "arrive_ts_right": 1659399317, "bs": "-"}, "2587814": {"name": "Vlad-the-Impala", "faction_id": 45507, "faction_name": "The Academy", "prize": 0, "prize_on_hand": 0, "prize_total": 0, "arrive_time": "08:19~08:35", "arrive_ts_left": 1659399564, "arrive_ts_right": 1659400520, "bs": "-"}, "2502546": {"name": "Yetzor", "faction_id": 33007, "faction_name": "HAKA", "prize": 0, "prize_on_hand": 0, "prize_total": 14739000, "arrive_time": "08:37~08:38", "arrive_ts_left": 1659400635, "arrive_ts_right": 1659400712, "bs": "-"}, "2454267": {"name": "DoryKitty", "faction_id": 46896, "faction_name": "The Amazonians", "prize": 0, "prize_on_hand": 0, "prize_total": 0, "arrive_time": "08:39~08:40", "arrive_ts_left": 1659400769, "arrive_ts_right": 1659400857, "bs": "-"}, "2186733": {"name": "Oxiiii", "faction_id": 16040, "faction_name": "Winter is Coming", "prize": 0, "prize_on_hand": 0, "prize_total": 13000000, "arrive_time": "08:39~08:41", "arrive_ts_left": 1659400777, "arrive_ts_right": 1659400867, "bs": "-"}, "2776617": {"name": "Nerdypeep", "faction_id": 11162, "faction_name": "NPO - Prosperity", "prize": 0, "prize_on_hand": 0, "prize_total": 0, "arrive_time": "08:37~08:38", "arrive_ts_left": 1659400639, "arrive_ts_right": 1659400719, "bs": "-"}, "2396542": {"name": "PapaZen", "faction_id": 8500, "faction_name": "Total Domination", "prize": 0, "prize_on_hand": 0, "prize_total": 0, "arrive_time": "08:37~08:38", "arrive_ts_left": 1659400638, "arrive_ts_right": 1659400718, "bs": "-"}, "2366870": {"name": "Rx7rudy", "faction_id": 16187, "faction_name": "Violent if Necessary  X", "prize": 0, "prize_on_hand": 0, "prize_total": 0, "arrive_time": "08:36~08:37", "arrive_ts_left": 1659400583, "arrive_ts_right": 1659400662, "bs": "-"}, "1989710": {"name": "chalky101", "faction_id": 36140, "faction_name": "Princess Dale&#039;s Beavers", "prize": 0, "prize_on_hand": 0, "prize_total": 0, "arrive_time": "08:20~08:35", "arrive_ts_left": 1659399631, "arrive_ts_right": 1659400557, "bs": "-"}, "2749020": {"name": "Jace9513", "faction_id": 43325, "faction_name": "Crime Syndicate", "prize": 0, "prize_on_hand": 0, "prize_total": 0, "arrive_time": "08:19~08:36", "arrive_ts_left": 1659399593, "arrive_ts_right": 1659400589, "bs": "-"}, "2346115": {"name": "revontcd", "faction_id": 12249, "faction_name": "Aurora Surrealis", "prize": 0, "prize_on_hand": 0, "prize_total": 0, "arrive_time": "08:39~08:41", "arrive_ts_left": 1659400777, "arrive_ts_right": 1659400866, "bs": "-"}, "2125465": {"name": "kyozo43", "faction_id": 25874, "faction_name": "Imminent Apocalypse", "prize": 0, "prize_on_hand": 0, "prize_total": 18000000, "arrive_time": "08:19~08:36", "arrive_ts_left": 1659399572, "arrive_ts_right": 1659400579, "bs": "-"}, "2634661": {"name": "Zargar", "faction_id": 39756, "faction_name": "Abusement Park", "prize": 3791010, "prize_on_hand": 0, "prize_total": 5631009, "arrive_time": "08:39~08:40", "arrive_ts_left": 1659400741, "arrive_ts_right": 1659400825, "bs": "-"}, "2605630": {"name": "mkr", "faction_id": 7986, "faction_name": "Assassin Team", "prize": 0, "prize_on_hand": 0, "prize_total": 0, "arrive_time": "08:19~08:36", "arrive_ts_left": 1659399579, "arrive_ts_right": 1659400601, "bs": "-"}, "2337524": {"name": "Lalala84", "faction_id": 23188, "faction_name": "Reign of Confusion", "prize": 0, "prize_on_hand": 0, "prize_total": 0, "arrive_time": "08:20~08:35", "arrive_ts_left": 1659399617, "arrive_ts_right": 1659400550, "bs": "-"}, "2673937": {"name": "Trom-Perie", "faction_id": 10818, "faction_name": "Lex Wolverines", "prize": 23058995, "prize_on_hand": 2444670, "prize_total": 25547665, "arrive_time": "08:37~08:39", "arrive_ts_left": 1659400625, "arrive_ts_right": 1659400788, "bs": "22.03m", "in_clothes": false}, "2604386": {"name": "OMW2FYB", "faction_id": 8766, "faction_name": "FLUX", "prize": 877250, "prize_on_hand": 17159950, "prize_total": 10019941764, "arrive_time": "08:20~08:36", "arrive_ts_left": 1659399623, "arrive_ts_right": 1659400573, "bs": "35.0m ~ 128.25m", "in_clothes": false}, "2756582": {"name": "_Farmer_Green_", "faction_id": 37595, "faction_name": "The Corporation", "prize": 0, "prize_on_hand": 0, "prize_total": 0, "arrive_time": "08:20~08:35", "arrive_ts_left": 1659399611, "arrive_ts_right": 1659400530, "bs": "-"}, "2592833": {"name": "Keyser_Soze", "faction_id": 9745, "faction_name": "Emergency Room", "prize": 1917000, "prize_on_hand": 0, "prize_total": 5964800, "arrive_time": "08:36~08:38", "arrive_ts_left": 1659400609, "arrive_ts_right": 1659400692, "bs": "-"}, "2779496": {"name": "Faenris", "faction_id": 9171, "faction_name": "Occultus", "prize": 0, "prize_on_hand": 0, "prize_total": 0, "arrive_time": "08:36~08:38", "arrive_ts_left": 1659400562, "arrive_ts_right": 1659400727, "bs": "-"}, "2428863": {"name": "Hovercat", "faction_id": 27351, "faction_name": "The New Mafia", "prize": 0, "prize_on_hand": 0, "prize_total": 82000, "arrive_time": "08:36~08:37", "arrive_ts_left": 1659400569, "arrive_ts_right": 1659400670, "bs": "-"}, "2775776": {"name": "ClarkOlofsson", "faction_id": 42605, "faction_name": "Cheeky Bananas", "prize": 0, "prize_on_hand": 0, "prize_total": 0, "arrive_time": "08:20~08:36", "arrive_ts_left": 1659399629, "arrive_ts_right": 1659400561, "bs": "-"}, "2316096": {"name": "TheWeedMan420", "faction_id": 45235, "faction_name": "The Cause.", "prize": 0, "prize_on_hand": 0, "prize_total": 0, "arrive_time": "08:20~08:35", "arrive_ts_left": 1659399624, "arrive_ts_right": 1659400527, "bs": "-"}, "2029956": {"name": "Tactical_Santa", "faction_id": 27312, "faction_name": "SA One  Punch", "prize": 3042099, "prize_on_hand": 0, "prize_total": 3042099, "arrive_time": "08:19~08:36", "arrive_ts_left": 1659399591, "arrive_ts_right": 1659400589, "bs": "-"}, "2479075": {"name": "Skyblue163", "faction_id": 9745, "faction_name": "Emergency Room", "prize": 93888, "prize_on_hand": 0, "prize_total": 4941776, "arrive_time": "08:19~08:35", "arrive_ts_left": 1659399556, "arrive_ts_right": 1659400520, "bs": "-"}, "2553990": {"name": "Fijiankai", "faction_id": 41956, "faction_name": "Path to Insanity", "prize": 1420000, "prize_on_hand": 41835000, "prize_total": 58963000, "arrive_time": "08:40~08:42", "arrive_ts_left": 1659400841, "arrive_ts_right": 1659400936, "bs": "250.0k ~ 388.47k", "in_clothes": false}, "2632654": {"name": "CastorP", "faction_id": 20501, "faction_name": "Unity", "prize": 0, "prize_on_hand": 0, "prize_total": 741000, "arrive_time": "08:40~08:42", "arrive_ts_left": 1659400837, "arrive_ts_right": 1659400935, "bs": "-"}, "2334040": {"name": "LaguTheBrown", "faction_id": 14760, "faction_name": "Dopeheads on Mopeds", "prize": 0, "prize_on_hand": 0, "prize_total": 0, "arrive_time": "08:40~08:59", "arrive_ts_left": 1659400844, "arrive_ts_right": 1659401970, "bs": "-"}, "2510544": {"name": "JasperLamarCrab", "faction_id": 39756, "faction_name": "Abusement Park", "prize": 0, "prize_on_hand": 0, "prize_total": 0, "arrive_time": "08:42~08:58", "arrive_ts_left": 1659400924, "arrive_ts_right": 1659401918, "bs": "-"}, "2717664": {"name": "Orapakata", "faction_id": 42650, "faction_name": "The Nights Watch", "prize": 0, "prize_on_hand": 0, "prize_total": 0, "arrive_time": "08:41~08:58", "arrive_ts_left": 1659400877, "arrive_ts_right": 1659401939, "bs": "-"}, "2320251": {"name": "UnderKitten", "faction_id": 9280, "faction_name": "Nomads Medical", "prize": 0, "prize_on_hand": 0, "prize_total": 0, "arrive_time": "08:41~08:58", "arrive_ts_left": 1659400904, "arrive_ts_right": 1659401921, "bs": "-"}, "2603615": {"name": "dc_angel", "faction_id": 16335, "faction_name": "SMTH - November Chopin", "prize": 0, "prize_on_hand": 0, "prize_total": 0, "arrive_time": "08:42~08:59", "arrive_ts_left": 1659400923, "arrive_ts_right": 1659401967, "bs": "-"}}, "raw_dict2": {"592667": {"name": "Wraith7n", "faction_id": 40420, "faction_name": "Too Sober for this Shit", "prize": 0, "prize_on_hand": 0, "prize_total": 48075000, "timestamp": 1659328090.96473, "bs": "2.89b", "in_clothes": false}, "2064856": {"name": "Savery", "faction_id": 12255, "faction_name": "Imperial MediHaven", "prize": 0, "prize_on_hand": 0, "prize_total": 1004005999, "timestamp": 1659337769.6677277, "bs": "1.45m ~ 2.0m", "in_clothes": false}, "1533238": {"name": "The_Convict", "faction_id": 45837, "faction_name": "dDossers", "prize": 0, "prize_on_hand": 0, "prize_total": 38300000, "timestamp": 1659338950.7546763, "bs": "1.42b", "in_clothes": false}, "2514533": {"name": "Mouradooo", "faction_id": 41748, "faction_name": "The Quietude", "prize": 0, "prize_on_hand": 0, "prize_total": 175065000, "timestamp": 1659364050.788431, "bs": "250.0k ~ 520.83k", "in_clothes": false}, "2567157": {"name": "MaDgamerr", "faction_id": 14820, "faction_name": "Unbroken Legion", "prize": 0, "prize_on_hand": 20893650, "prize_total": 7042853650, "timestamp": 1659367992.8941422, "bs": "95.53k ~ 200.0k", "in_clothes": false}, "1716924": {"name": "Benedetta", "faction_id": 9280, "faction_name": "Nomads Medical", "prize": 0, "prize_on_hand": 0, "prize_total": 1302993400, "timestamp": 1659369094.3929005, "bs": "174.48k ~ 2.0m", "in_clothes": false}, "2753939": {"name": "iceman01", "faction_id": 40242, "faction_name": "Canes Belli", "prize": 0, "prize_on_hand": 0, "prize_total": 1115959111, "timestamp": 1659373168.729513, "bs": "25.0k ~ 173.73k", "in_clothes": false}, "110507": {"name": "psycholist", "faction_id": 12190, "faction_name": "KILL2WIN", "prize": 0, "prize_on_hand": 0, "prize_total": 81560000, "timestamp": 1659374585.934939, "bs": "1.74b", "in_clothes": false}, "2150066": {"name": "Death_Back", "faction_id": 25025, "faction_name": "DP Warriors", "prize": 0, "prize_on_hand": 0, "prize_total": 9999999999, "timestamp": 1659374601.1023724, "bs": "35.0m ~ 416.69m", "in_clothes": false}, "1089425": {"name": "Master-of-King", "faction_id": 38319, "faction_name": "Friday 13", "prize": 0, "prize_on_hand": 5845000, "prize_total": 1005845000, "timestamp": 1659381938.215364, "bs": "114.63m", "in_clothes": false}, "2642145": {"name": "Jackeman", "faction_id": 9405, "faction_name": "Plata X", "prize": 0, "prize_on_hand": 0, "prize_total": 43969913, "timestamp": 1659381983.0911477, "bs": "33.33m", "in_clothes": false}, "1283458": {"name": "thelone", "faction_id": 16296, "faction_name": "School of Devlins", "prize": 0, "prize_on_hand": 0, "prize_total": 6132978900, "timestamp": 1659385707.0173302, "bs": "11.26m ~ 20.0m", "in_clothes": false}, "1988228": {"name": "TinyBrain", "faction_id": 9036, "faction_name": "The Black Pearl", "prize": 0, "prize_on_hand": 0, "prize_total": 190000000, "timestamp": 1659389716.7890368, "bs": "701.93m", "in_clothes": false}, "2545294": {"name": "ThePotatoSage", "faction_id": 13737, "faction_name": "The War Rig", "prize": 0, "prize_on_hand": 0, "prize_total": 1364098128, "timestamp": 1659391195.6946862, "bs": "2.5m ~ 2.52m", "in_clothes": false}, "2249396": {"name": "Mrs_Battery", "faction_id": 15929, "faction_name": "The Inquisition", "prize": 0, "prize_on_hand": 0, "prize_total": 120650000, "timestamp": 1659391200.7892797, "bs": "1.66m", "in_clothes": false}, "1901618": {"name": "LilSwagglet", "faction_id": 32585, "faction_name": "Heart of a Pirate", "prize": 0, "prize_on_hand": 0, "prize_total": 188011000, "timestamp": 1659393717.5483873, "bs": "47.02m", "in_clothes": false}, "2652804": {"name": "BoQuA", "faction_id": 41238, "faction_name": "The Mile High Club", "prize": 0, "prize_on_hand": 0, "prize_total": 694003036, "timestamp": 1659393720.951136, "bs": "2.5m ~ 6.51m", "in_clothes": false}, "1949097": {"name": "Uriah", "faction_id": 14581, "faction_name": "Stygian: Underworld", "prize": 0, "prize_on_hand": 0, "prize_total": 471793690, "timestamp": 1659395081.6002834, "bs": "2.76b", "in_clothes": false}, "2556413": {"name": "Himawami", "faction_id": 43226, "faction_name": "Gentleman Bastards", "prize": 0, "prize_on_hand": 0, "prize_total": 110000000, "timestamp": 1659395092.7608163, "bs": "12.89m", "in_clothes": false}, "2727293": {"name": "Pundarn", "faction_id": 12249, "faction_name": "Aurora Surrealis", "prize": 0, "prize_on_hand": 0, "prize_total": 7001610001, "timestamp": 1659396057.4081078, "bs": "1.42m", "in_clothes": false}, "2482139": {"name": "Yiannisk", "faction_id": 33783, "faction_name": "Impulse", "prize": 0, "prize_on_hand": 0, "prize_total": 22100000, "timestamp": 1659396064.0337927, "bs": "1.02b", "in_clothes": false}, "2101940": {"name": "xenagos", "faction_id": 10818, "faction_name": "Lex Wolverines", "prize": 0, "prize_on_hand": 0, "prize_total": 34239000, "timestamp": 1659396380.8069084, "bs": "250.0m ~ 572.39m", "in_clothes": false}, "2428109": {"name": "JFelix", "faction_id": 16120, "faction_name": "Stoners Reeking Havoc", "prize": 0, "prize_on_hand": 0, "prize_total": 21096000, "timestamp": 1659396386.606595, "bs": "782.47k", "in_clothes": false}, "2073052": {"name": "playtorn17", "faction_id": 8938, "faction_name": "Arcadia", "prize": 0, "prize_on_hand": 0, "prize_total": 1500790000, "timestamp": 1659397650.437462, "bs": "2.08b", "in_clothes": false}, "660616": {"name": "ianstewart", "faction_id": 8181, "faction_name": "Travellers Paradise", "prize": 0, "prize_on_hand": 0, "prize_total": 26764500, "timestamp": 1659397670.1717086, "bs": "13.84b", "in_clothes": false}, "2701090": {"name": "Xxxmizmiixxx", "faction_id": 27223, "faction_name": "Little Stompers", "prize": 0, "prize_on_hand": 28581900, "prize_total": 35478700, "timestamp": 1659398929.0779533, "bs": "1.41m", "in_clothes": false}, "2693902": {"name": "Krythos", "faction_id": 8715, "faction_name": "Midnight X", "prize": 0, "prize_on_hand": 13640000, "prize_total": 30881743, "timestamp": 1659398936.9372504, "bs": "5.06m", "in_clothes": false}, "1342911": {"name": "123tomek", "faction_id": 37149, "faction_name": "Dream Team", "prize": 0, "prize_on_hand": 0, "prize_total": 27649971, "timestamp": 1659398941.260953, "bs": "1.22m", "in_clothes": false}, "2152982": {"name": "ILLUSIONIST", "faction_id": 9577, "faction_name": "PIHB", "prize": 0, "prize_on_hand": 0, "prize_total": 2021199979788, "timestamp": 1659398945.7157974, "bs": "35.0m ~ 100.83m", "in_clothes": false}, "852647": {"name": "johnisbubba", "faction_id": 231, "faction_name": "Destructive Anomaly", "prize": 0, "prize_on_hand": 0, "prize_total": 525000000, "timestamp": 1659399262.0691915, "bs": "4.13b", "in_clothes": false}, "2424553": {"name": "HarisRosa", "faction_id": 22932, "faction_name": "No Signal", "prize": 14400000, "prize_on_hand": 0, "prize_total": 24820000, "timestamp": 1659400156.7070217, "bs": "421.77k", "in_clothes": false}, "2750904": {"name": "Trevor_", "faction_id": 20514, "faction_name": "Brahmastra", "prize": 0, "prize_on_hand": 0, "prize_total": 22165007, "timestamp": 1659400158.6766431, "bs": "296.75k", "in_clothes": false}, "2058764": {"name": "Sanddragon72", "faction_id": 8803, "faction_name": "Buttgrass Inc", "prize": 1825000, "prize_on_hand": 2131500, "prize_total": 25829500, "timestamp": 1659400159.7082572, "bs": "973.84m", "in_clothes": false}, "2363236": {"name": "Luckrook", "faction_id": 33241, "faction_name": "Nub Navy", "prize": 0, "prize_on_hand": 0, "prize_total": 117649867, "timestamp": 1659400164.6595595, "bs": "35.0m ~ 182.25m", "in_clothes": false}, "479467": {"name": "InkMachine", "faction_id": 8510, "faction_name": "Ara Pacis", "prize": 0, "prize_on_hand": 0, "prize_total": 1100000000, "timestamp": 1659400176.1690648, "bs": "1.45b", "in_clothes": false}, "2625662": {"name": "quillame", "faction_id": 35507, "faction_name": "The Nest", "prize": 0, "prize_on_hand": 0, "prize_total": 793014614, "timestamp": 1659400489.6812987, "bs": "708.77m", "in_clothes": false}}, "raw_dict3": {"2621009": {"name": "Oopsxo", "faction_id": 38547, "faction_name": "The Rusty Pickle", "prize": 3400220, "prize_on_hand": 0, "prize_total": 149600695, "arrive_time": "07:36~07:53", "arrive_ts_left": 1659396996, "arrive_ts_right": 1659398003, "timestamp": 1659385740.7536564, "bs": "2.5m ~ 4.01m", "in_clothes": false}, "2650236": {"name": "Tejas", "faction_id": 28205, "faction_name": "Invictus", "prize": 11551819, "prize_on_hand": 103096509, "prize_total": 103096509, "arrive_time": "08:20~08:36", "arrive_ts_left": 1659399604, "arrive_ts_right": 1659400565, "timestamp": 1659388512.5022743, "bs": "2.5m ~ 4.63m"}, "1873621": {"name": "sprulesy", "faction_id": 22492, "faction_name": "Dystopia", "prize": 0, "prize_on_hand": 5069500, "prize_total": 163901498, "arrive_time": "08:19~08:35", "arrive_ts_left": 1659399573, "arrive_ts_right": 1659400550, "timestamp": 1659388526.950446, "bs": "96.16m"}, "2662882": {"name": "DingoTM", "faction_id": 39756, "faction_name": "Abusement Park", "prize": 0, "prize_on_hand": 0, "prize_total": 26721901, "arrive_time": "08:39~08:40", "arrive_ts_left": 1659400741, "arrive_ts_right": 1659400825, "timestamp": 1659388543.1557143, "bs": "2.5m ~ 12.84m", "in_clothes": false}, "2635264": {"name": "Jawl", "faction_id": 13737, "faction_name": "The War Rig", "prize": 5400000, "prize_on_hand": 0, "prize_total": 22751900, "arrive_time": "08:20~08:36", "arrive_ts_left": 1659399637, "arrive_ts_right": 1659400560, "timestamp": 1659388544.9049358, "bs": "250.0k ~ 335.22k", "in_clothes": false}, "2570196": {"name": "GmProdigy", "faction_id": 20747, "faction_name": "Damage Inc", "prize": 0, "prize_on_hand": 0, "prize_total": 1145699372, "arrive_time": "08:42~08:59", "arrive_ts_left": 1659400924, "arrive_ts_right": 1659401955, "timestamp": 1659389708.30773, "bs": "863.02m"}, "2635747": {"name": "netmind", "faction_id": 30695, "faction_name": "Killer bee recruit", "prize": 16150000, "prize_on_hand": 0, "prize_total": 30073000, "arrive_time": "08:41~08:58", "arrive_ts_left": 1659400895, "arrive_ts_right": 1659401886, "timestamp": 1659389715.9602325, "bs": "250.0k ~ 832.18k"}, "2563963": {"name": "sw19womble", "faction_id": 1117, "faction_name": "The Saviors", "prize": 0, "prize_on_hand": 0, "prize_total": 50100000, "arrive_time": "08:42~08:58", "arrive_ts_left": 1659400929, "arrive_ts_right": 1659401910, "timestamp": 1659389724.44316, "bs": "733.27m", "in_clothes": false}, "2543287": {"name": "Mixmasterrub", "faction_id": 10566, "faction_name": "The Rifle Company", "prize": 0, "prize_on_hand": 0, "prize_total": 1000555000, "arrive_time": "09:25~09:27", "arrive_ts_left": 1659403544, "arrive_ts_right": 1659403637, "timestamp": 1659391582.9690113, "bs": "991.83m", "in_clothes": false}, "2623275": {"name": "-Bishop-", "faction_id": 10174, "faction_name": "The Quidnunks HQ", "prize": 0, "prize_on_hand": 125000000, "prize_total": 746020000, "arrive_time": "09:27~09:43", "arrive_ts_left": 1659403635, "arrive_ts_right": 1659404593, "timestamp": 1659392285.5743434, "bs": "101.0m"}, "2687051": {"name": "TRSkyFox", "faction_id": 10741, "faction_name": "SMTH - Trisolary", "prize": 0, "prize_on_hand": 0, "prize_total": 59376101, "arrive_time": "09:26~09:43", "arrive_ts_left": 1659403598, "arrive_ts_right": 1659404611, "timestamp": 1659392311.7926772, "bs": "11.84m", "in_clothes": false}, "1338804": {"name": "cockroach", "faction_id": 230, "faction_name": "PT-Family", "prize": 0, "prize_on_hand": 0, "prize_total": 9743973041, "arrive_time": "09:26~09:43", "arrive_ts_left": 1659403603, "arrive_ts_right": 1659404617, "timestamp": 1659392312.6662867, "bs": "7.62b", "in_clothes": false}, "2159586": {"name": "Peanutdaking", "faction_id": 8819, "faction_name": "Violent if Necessary", "prize": 0, "prize_on_hand": 51643365, "prize_total": 143117644, "arrive_time": "09:44~09:45", "arrive_ts_left": 1659404650, "arrive_ts_right": 1659404736, "timestamp": 1659392670.117488, "bs": "653.33m"}, "2196930": {"name": "Mercurian", "faction_id": 11279, "faction_name": "Avaritia", "prize": 0, "prize_on_hand": 0, "prize_total": 16979164650, "arrive_time": "09:27~09:45", "arrive_ts_left": 1659403631, "arrive_ts_right": 1659404736, "timestamp": 1659392676.9513555, "bs": "317.74m", "in_clothes": false}, "331351": {"name": "blast_dragon", "faction_id": 40959, "faction_name": "Epic Mafia", "prize": 0, "prize_on_hand": 0, "prize_total": 1000000000, "arrive_time": "09:44~09:45", "arrive_ts_left": 1659404671, "arrive_ts_right": 1659404758, "timestamp": 1659392677.8113956, "bs": "1.2b", "in_clothes": false}, "2539511": {"name": "GR33NM4MB4", "faction_id": 6799, "faction_name": "The Untouchables", "prize": 0, "prize_on_hand": 66726580, "prize_total": 252570143, "arrive_time": "09:48~10:05", "arrive_ts_left": 1659404905, "arrive_ts_right": 1659405948, "timestamp": 1659393726.0439694, "bs": "250.0m ~ 275.12m"}, "2606891": {"name": "MSI", "faction_id": 13307, "faction_name": "Plata O Pelusa", "prize": 0, "prize_on_hand": 0, "prize_total": 542258945, "arrive_time": "09:49~10:04", "arrive_ts_left": 1659404964, "arrive_ts_right": 1659405892, "timestamp": 1659393732.0152433, "bs": "431.65m"}, "2112183": {"name": "sTrOb", "faction_id": 8397, "faction_name": "ilimitada", "prize": 0, "prize_on_hand": 0, "prize_total": 969919191, "arrive_time": "09:49~10:05", "arrive_ts_left": 1659404944, "arrive_ts_right": 1659405929, "timestamp": 1659393732.8576834, "bs": "2.25b"}, "1739168": {"name": "bodiekater0830", "faction_id": 43048, "faction_name": "The Lost Boys", "prize": 3291254, "prize_on_hand": 0, "prize_total": 315009432, "arrive_time": "09:44~10:05", "arrive_ts_left": 1659404656, "arrive_ts_right": 1659405919, "timestamp": 1659393742.2507746, "bs": "2.5m ~ 36.4m", "in_clothes": false}, "2699540": {"name": "kirada", "faction_id": 46708, "faction_name": "Fibonacci", "prize": 0, "prize_on_hand": 0, "prize_total": 41885000, "arrive_time": "09:48~10:05", "arrive_ts_left": 1659404930, "arrive_ts_right": 1659405953, "timestamp": 1659393743.1400077, "bs": "250.0k ~ 281.66k", "in_clothes": false}, "2201418": {"name": "ThaWh1teSki7tle", "faction_id": 40431, "faction_name": "The White House", "prize": 51000000, "prize_on_hand": 10200000, "prize_total": 51000000, "arrive_time": "09:46~10:04", "arrive_ts_left": 1659404815, "arrive_ts_right": 1659405894, "timestamp": 1659393743.9843926, "bs": "2.5m ~ 2.78m", "in_clothes": false}, "2357595": {"name": "Meo-mcano", "faction_id": 45797, "faction_name": "Oreo Cheesecake", "prize": 0, "prize_on_hand": 0, "prize_total": 358300001, "arrive_time": "10:10~10:26", "arrive_ts_left": 1659406210, "arrive_ts_right": 1659407179, "timestamp": 1659394755.392594, "bs": "1.33b"}, "2155610": {"name": "SuperSanta", "faction_id": 16282, "faction_name": "Nuclear Winter", "prize": 25472500, "prize_on_hand": 0, "prize_total": 89264500, "arrive_time": "10:10~10:26", "arrive_ts_left": 1659406223, "arrive_ts_right": 1659407180, "timestamp": 1659394757.0794635, "bs": "752.31m", "in_clothes": false}, "1979128": {"name": "LovelyWrain", "faction_id": 33783, "faction_name": "Impulse", "prize": 0, "prize_on_hand": 0, "prize_total": 136589500, "arrive_time": "10:29~10:30", "arrive_ts_left": 1659407358, "arrive_ts_right": 1659407443, "timestamp": 1659395100.4637103, "bs": "2.73b", "in_clothes": false}, "21208": {"name": "Crawdacity", "faction_id": 33007, "faction_name": "HAKA", "prize": 0, "prize_on_hand": 0, "prize_total": 46034905, "arrive_time": "10:10~10:27", "arrive_ts_left": 1659406219, "arrive_ts_right": 1659407241, "timestamp": 1659395101.6513581, "bs": "3.39b", "in_clothes": false}, "2553102": {"name": "Taro83", "faction_id": 13737, "faction_name": "The War Rig", "prize": 0, "prize_on_hand": 0, "prize_total": 44330900, "arrive_time": "10:26~10:28", "arrive_ts_left": 1659407213, "arrive_ts_right": 1659407304, "timestamp": 1659395102.495782, "bs": "14.94m", "in_clothes": false}, "2200342": {"name": "Naruto21", "faction_id": 8317, "faction_name": "Naughty Souls", "prize": 0, "prize_on_hand": 0, "prize_total": 27000000, "arrive_time": "10:11~10:27", "arrive_ts_left": 1659406286, "arrive_ts_right": 1659407227, "timestamp": 1659395103.3713567, "bs": "304.31m", "in_clothes": false}, "2280531": {"name": "Sweetpatches", "faction_id": 10820, "faction_name": "Carbon Penguins", "prize": 1935900, "prize_on_hand": 32003923, "prize_total": 34392583, "arrive_time": "10:11~10:26", "arrive_ts_left": 1659406269, "arrive_ts_right": 1659407212, "timestamp": 1659395104.247982, "bs": "663.3m", "in_clothes": false}, "2052857": {"name": "ContractKiller", "faction_id": 16312, "faction_name": "39th Street Killers X", "prize": 0, "prize_on_hand": 0, "prize_total": 1030740999, "arrive_time": "10:33~10:48", "arrive_ts_left": 1659407581, "arrive_ts_right": 1659408495, "timestamp": 1659396064.889577, "bs": "2.92b", "in_clothes": false}, "2489523": {"name": "Doc_Holiday949", "faction_id": 44758, "faction_name": "NPO - Strength", "prize": 549989, "prize_on_hand": 0, "prize_total": 25850372, "arrive_time": "10:31~10:49", "arrive_ts_left": 1659407517, "arrive_ts_right": 1659408544, "timestamp": 1659396397.5450916, "bs": "783.14m", "in_clothes": false}, "2130543": {"name": "ablindman", "faction_id": 12255, "faction_name": "Imperial MediHaven", "prize": 0, "prize_on_hand": 0, "prize_total": 20900000, "arrive_time": "10:33~10:48", "arrive_ts_left": 1659407586, "arrive_ts_right": 1659408513, "timestamp": 1659396398.3875303, "bs": "35.0m ~ 101.44m", "in_clothes": false}, "1690688": {"name": "Unl3asheD", "faction_id": 14078, "faction_name": "~Twisted~", "prize": 0, "prize_on_hand": 0, "prize_total": 20000000, "arrive_time": "10:32~10:49", "arrive_ts_left": 1659407554, "arrive_ts_right": 1659408552, "timestamp": 1659396399.2475114, "bs": "2.81b", "in_clothes": false}, "2122284": {"name": "NiceOn", "faction_id": 12094, "faction_name": "Nuclear Fusion", "prize": 0, "prize_on_hand": 0, "prize_total": 305172345, "arrive_time": "10:52~10:53", "arrive_ts_left": 1659408747, "arrive_ts_right": 1659408838, "timestamp": 1659396714.3457377, "bs": "3.16b", "in_clothes": false}, "2574041": {"name": "GlassSteel", "faction_id": 18736, "faction_name": "Monarch Research", "prize": 0, "prize_on_hand": 0, "prize_total": 75000000, "arrive_time": "10:54~11:09", "arrive_ts_left": 1659408840, "arrive_ts_right": 1659409797, "timestamp": 1659397649.6106138, "bs": "879.85m"}, "1880065": {"name": "-Titanium-", "faction_id": 11356, "faction_name": "-UGK-", "prize": 25339993, "prize_on_hand": 0, "prize_total": 27215993, "arrive_time": "11:12~11:13", "arrive_ts_left": 1659409930, "arrive_ts_right": 1659410027, "timestamp": 1659397671.4217293, "bs": "1.66b", "in_clothes": false}, "2227618": {"name": "-proteus-", "faction_id": 17589, "faction_name": "Illuminati Familia", "prize": 0, "prize_on_hand": 0, "prize_total": 39024998, "arrive_time": "10:52~11:15", "arrive_ts_left": 1659408766, "arrive_ts_right": 1659410137, "timestamp": 1659397985.3075132, "bs": "250.0m ~ 609.08m", "in_clothes": false}, "1937319": {"name": "Nalice", "faction_id": 46089, "faction_name": "Shiba Inu", "prize": 0, "prize_on_hand": 0, "prize_total": 28610000, "arrive_time": "11:13~11:15", "arrive_ts_left": 1659410012, "arrive_ts_right": 1659410122, "timestamp": 1659397986.1811264, "bs": "79.04m", "in_clothes": false}, "2544877": {"name": "Seflapod", "faction_id": 16296, "faction_name": "School of Devlins", "prize": 9091350, "prize_on_hand": 562400, "prize_total": 25779438, "arrive_time": "11:14~11:16", "arrive_ts_left": 1659410078, "arrive_ts_right": 1659410189, "timestamp": 1659397987.0099332, "bs": "2.5m ~ 7.06m", "in_clothes": false}, "2304442": {"name": "-Germs", "faction_id": 95, "faction_name": "MORTAL LEGENDS", "prize": 0, "prize_on_hand": 0, "prize_total": 3333333333, "arrive_time": "11:15~11:32", "arrive_ts_left": 1659410146, "arrive_ts_right": 1659411172, "timestamp": 1659398946.5758135, "bs": "219.97m", "in_clothes": false}, "2310238": {"name": "Waffles", "faction_id": 7002, "faction_name": "Karma Chameleons", "prize": 840000, "prize_on_hand": 14206000, "prize_total": 21072000, "arrive_time": "11:15~11:33", "arrive_ts_left": 1659410131, "arrive_ts_right": 1659411187, "timestamp": 1659398947.453388, "bs": "35.0m ~ 42.23m", "in_clothes": false}, "2410926": {"name": "Seven_Lucky_God", "faction_id": 14821, "faction_name": "Caledonia", "prize": 4262500, "prize_on_hand": 0, "prize_total": 181880328, "arrive_time": "11:15~11:32", "arrive_ts_left": 1659410143, "arrive_ts_right": 1659411170, "timestamp": 1659398948.2978005, "bs": "1.07b", "in_clothes": false}, "2500470": {"name": "Serviens", "faction_id": 25025, "faction_name": "DP Warriors", "prize": 0, "prize_on_hand": 0, "prize_total": 20735000, "arrive_time": "11:37~11:52", "arrive_ts_left": 1659411473, "arrive_ts_right": 1659412353, "timestamp": 1659400180.2175505, "bs": "2.5m ~ 65.33m"}, "2484589": {"name": "moring", "faction_id": 10741, "faction_name": "SMTH - Trisolary", "prize": 0, "prize_on_hand": 0, "prize_total": 102795000, "arrive_time": "11:36~11:52", "arrive_ts_left": 1659411400, "arrive_ts_right": 1659412347, "timestamp": 1659400183.3767827, "bs": "91.71m", "in_clothes": false}, "727005": {"name": "imezi", "faction_id": 9110, "faction_name": "Oligarch", "prize": 0, "prize_on_hand": 450000, "prize_total": 189415182, "arrive_time": "11:54~11:55", "arrive_ts_left": 1659412461, "arrive_ts_right": 1659412552, "timestamp": 1659400184.3907983, "bs": "3.31b", "in_clothes": false}, "2038227": {"name": "tejdog1", "faction_id": 18736, "faction_name": "Monarch Research", "prize": 0, "prize_on_hand": 0, "prize_total": 12748987145, "arrive_time": "11:37~11:53", "arrive_ts_left": 1659411451, "arrive_ts_right": 1659412426, "timestamp": 1659400185.48478, "bs": "3.59b", "in_clothes": false}, "2203318": {"name": "smack534", "faction_id": 39960, "faction_name": "Brave Survivors", "prize": 0, "prize_on_hand": 0, "prize_total": 22038250, "arrive_time": "11:37~11:53", "arrive_ts_left": 1659411421, "arrive_ts_right": 1659412414, "timestamp": 1659400186.9220052, "bs": "250.0m ~ 503.02m", "in_clothes": false}}}, "China": {"raw_dict1": {"2511247": {"name": "Vyvydra", "faction_id": 13041, "faction_name": "Crime Monasterio", "prize": 0, "prize_on_hand": 0, "prize_total": 2202000, "arrive_time": "07:13~07:37", "arrive_ts_left": 1659395635, "arrive_ts_right": 1659397045, "bs": "-"}, "2766976": {"name": "Gcraft", "faction_id": 45835, "faction_name": "Fallen Angels Syndicate", "prize": 0, "prize_on_hand": 0, "prize_total": 0, "arrive_time": "07:41~07:57", "arrive_ts_left": 1659397300, "arrive_ts_right": 1659398247, "bs": "-"}}, "raw_dict2": {"2268574": {"name": "Goomonryong", "faction_id": 16443, "faction_name": "Vietgang", "prize": 0, "prize_on_hand": 0, "prize_total": 2000000000, "timestamp": 1659386932.7463348, "bs": "35.0m ~ 175.19m", "in_clothes": false}, "1627725": {"name": "Thade", "faction_id": 9036, "faction_name": "The Black Pearl", "prize": 0, "prize_on_hand": 0, "prize_total": 66750000, "timestamp": 1659397625.2789423, "bs": "1.78b", "in_clothes": false}, "2701064": {"name": "deNKaw", "faction_id": 44467, "faction_name": "The Hogs", "prize": 0, "prize_on_hand": 39480, "prize_total": 120572477, "timestamp": 1659398778.5289288, "bs": "1.23m", "in_clothes": false}, "2801616": {"name": "ChainedCrow", "faction_id": 8317, "faction_name": "Naughty Souls", "prize": 0, "prize_on_hand": 0, "prize_total": 1000000000, "timestamp": 1659399062.387673, "bs": "6.79k", "in_clothes": false}}, "raw_dict3": {"1598789": {"name": "jakariel", "faction_id": 525, "faction_name": "EQ: Ministry of Mayhem", "prize": 7405500, "prize_on_hand": 435000, "prize_total": 2069461856, "arrive_time": "08:02~08:19", "arrive_ts_left": 1659398524, "arrive_ts_right": 1659399581, "timestamp": 1659389542.9684856, "bs": "1.15m ~ 20.0m"}, "2077736": {"name": "Mersh", "faction_id": 89, "faction_name": "Catalysis", "prize": 0, "prize_on_hand": 0, "prize_total": 2000000000, "arrive_time": "08:25~08:43", "arrive_ts_left": 1659399943, "arrive_ts_right": 1659401030, "timestamp": 1659391076.5473757, "bs": "3.06b", "in_clothes": false}, "2711485": {"name": "Purple_Orange", "faction_id": 9176, "faction_name": "The Iron Fist", "prize": 0, "prize_on_hand": 0, "prize_total": 416436064, "arrive_time": "09:09~09:26", "arrive_ts_left": 1659402562, "arrive_ts_right": 1659403564, "timestamp": 1659393684.8910413, "bs": "1.71m"}, "2189162": {"name": "Damaja75", "faction_id": 8938, "faction_name": "Arcadia", "prize": 4135342, "prize_on_hand": 0, "prize_total": 20915342, "arrive_time": "09:46~09:48", "arrive_ts_left": 1659404814, "arrive_ts_right": 1659404912, "timestamp": 1659394827.3268201, "bs": "1.23b"}, "2176496": {"name": "Moxy88", "faction_id": 8317, "faction_name": "Naughty Souls", "prize": 0, "prize_on_hand": 0, "prize_total": 27000000, "arrive_time": "09:32~09:48", "arrive_ts_left": 1659403946, "arrive_ts_right": 1659404887, "timestamp": 1659394838.483423, "bs": "35.0m ~ 304.7m"}, "298931": {"name": "HeroponRiki", "faction_id": 11747, "faction_name": "Natural Selection II", "prize": 0, "prize_on_hand": 0, "prize_total": 9999999999, "arrive_time": "09:32~09:47", "arrive_ts_left": 1659403948, "arrive_ts_right": 1659404839, "timestamp": 1659394845.5310667, "bs": "9.68b"}, "2286472": {"name": "Nick969", "faction_id": 95, "faction_name": "MORTAL LEGENDS", "prize": 4100000, "prize_on_hand": 0, "prize_total": 35795798, "arrive_time": "09:51~09:52", "arrive_ts_left": 1659405082, "arrive_ts_right": 1659405172, "timestamp": 1659395127.9978654, "bs": "869.4m", "in_clothes": true}, "2212764": {"name": "541fatkid", "faction_id": 16120, "faction_name": "Stoners Reeking Havoc", "prize": 0, "prize_on_hand": 0, "prize_total": 351950000, "arrive_time": "09:49~09:50", "arrive_ts_left": 1659404947, "arrive_ts_right": 1659405049, "timestamp": 1659395128.824698, "bs": "35.0m ~ 334.05m", "in_clothes": false}, "2438366": {"name": "Rasselbock", "faction_id": 30009, "faction_name": "White Rabbits", "prize": 10687939, "prize_on_hand": 0, "prize_total": 237357772, "arrive_time": "09:49~09:51", "arrive_ts_left": 1659404990, "arrive_ts_right": 1659405077, "timestamp": 1659395129.6691172, "bs": "1.43b", "in_clothes": false}, "828140": {"name": "valentinos", "faction_id": 11747, "faction_name": "Natural Selection II", "prize": 0, "prize_on_hand": 1078000, "prize_total": 38950000, "arrive_time": "09:53~10:10", "arrive_ts_left": 1659405196, "arrive_ts_right": 1659406201, "timestamp": 1659396240.073985, "bs": "10.16b"}, "2702527": {"name": "ZorroBadger", "faction_id": 8867, "faction_name": "Razers", "prize": 0, "prize_on_hand": 0, "prize_total": 1100000000, "arrive_time": "09:52~10:08", "arrive_ts_left": 1659405173, "arrive_ts_right": 1659406139, "timestamp": 1659396266.8575256, "bs": "1.43m", "in_clothes": false}, "2508857": {"name": "Lorazepam", "faction_id": 8836, "faction_name": "Vinerri", "prize": 0, "prize_on_hand": 0, "prize_total": 1187420420, "arrive_time": "09:53~10:09", "arrive_ts_left": 1659405197, "arrive_ts_right": 1659406165, "timestamp": 1659396267.748739, "bs": "250.0m ~ 532.69m", "in_clothes": false}, "2505217": {"name": "ivanture", "faction_id": 9055, "faction_name": "Natural Selection IV", "prize": 0, "prize_on_hand": 0, "prize_total": 34125000, "arrive_time": "10:14~10:31", "arrive_ts_left": 1659406466, "arrive_ts_right": 1659407475, "timestamp": 1659397623.6213236, "bs": "746.78m"}, "2198959": {"name": "Kkaos420", "faction_id": 6731, "faction_name": "The Next Level", "prize": 0, "prize_on_hand": 0, "prize_total": 180252775, "arrive_time": "10:15~10:31", "arrive_ts_left": 1659406547, "arrive_ts_right": 1659407497, "timestamp": 1659397637.7020776, "bs": "2.4b", "in_clothes": false}, "2727668": {"name": "MQJunior", "faction_id": 46708, "faction_name": "Fibonacci", "prize": 0, "prize_on_hand": 0, "prize_total": 20147500, "arrive_time": "10:36~10:53", "arrive_ts_left": 1659407796, "arrive_ts_right": 1659408806, "timestamp": 1659398776.7953107, "bs": "250.0k ~ 432.69k"}, "1627352": {"name": "TheCaporegime", "faction_id": 9517, "faction_name": "OverWatch", "prize": 0, "prize_on_hand": 0, "prize_total": 1000000000, "arrive_time": "10:59~11:13", "arrive_ts_left": 1659409140, "arrive_ts_right": 1659410005, "timestamp": 1659400112.5065293, "bs": "250.0m ~ 483.96m", "in_clothes": false}}}, "Argentina": {"raw_dict1": {}, "raw_dict2": {"2330900": {"name": "Reevaa", "faction_id": 8151, "faction_name": "LONDON", "prize": 3600000, "prize_on_hand": 1500000, "prize_total": 23653500, "timestamp": 1659368957.9235086, "bs": "1.05b", "in_clothes": false}, "2195416": {"name": "xXx1", "faction_id": 17587, "faction_name": "Nomads 2.0", "prize": 0, "prize_on_hand": 0, "prize_total": 67355400, "timestamp": 1659371619.3685486, "bs": "67.53m", "in_clothes": false}, "1187753": {"name": "lwanyatermyarpi", "faction_id": 8255, "faction_name": "Anarchy", "prize": 0, "prize_on_hand": 0, "prize_total": 23700000, "timestamp": 1659383538.529268, "bs": "250.0k ~ 1.16m", "in_clothes": false}, "1849958": {"name": "girtepo", "faction_id": 10913, "faction_name": "Unbroken Silence", "prize": 0, "prize_on_hand": 0, "prize_total": 55370000, "timestamp": 1659386962.3606927, "bs": "129.87m ~ 200.0m", "in_clothes": false}, "2270765": {"name": "Vigor", "faction_id": 12893, "faction_name": "Darkside", "prize": 0, "prize_on_hand": 0, "prize_total": 2698805000, "timestamp": 1659386986.7019234, "bs": "250.0m ~ 731.41m", "in_clothes": false}, "2153592": {"name": "OGColossus", "faction_id": 17001, "faction_name": "Trigger Happy Devils", "prize": 0, "prize_on_hand": 0, "prize_total": 129111111, "timestamp": 1659388195.5246327, "bs": "501.67m", "in_clothes": false}, "2140678": {"name": "yalex13d", "faction_id": 7986, "faction_name": "Assassin Team", "prize": 0, "prize_on_hand": 0, "prize_total": 26410000, "timestamp": 1659394797.7838542, "bs": "967.84m", "in_clothes": false}}, "raw_dict3": {"1896913": {"name": "Alabama_Hammah", "faction_id": 38668, "faction_name": "Valhalla - Barna", "prize": 5539000, "prize_on_hand": 8200, "prize_total": 122170055, "arrive_time": "08:40~08:54", "arrive_ts_left": 1659400826, "arrive_ts_right": 1659401694, "timestamp": 1659394810.3253849, "bs": "2.45b", "in_clothes": false}, "1237996": {"name": "Jack-Bauer", "faction_id": 14078, "faction_name": "~Twisted~", "prize": 4250000, "prize_on_hand": 0, "prize_total": 91143895, "arrive_time": "09:01~09:18", "arrive_ts_left": 1659402094, "arrive_ts_right": 1659403092, "timestamp": 1659396197.7174568, "bs": "6.98b"}, "449998": {"name": "Zmobie", "faction_id": 19, "faction_name": "39th Street Killers", "prize": 0, "prize_on_hand": 0, "prize_total": 10000000000, "arrive_time": "09:01~09:17", "arrive_ts_left": 1659402065, "arrive_ts_right": 1659403063, "timestamp": 1659396201.8771143, "bs": "1.23b", "in_clothes": false}, "2069985": {"name": "kolisavra", "faction_id": 6799, "faction_name": "The Untouchables", "prize": 9981920, "prize_on_hand": 0, "prize_total": 922447294, "arrive_time": "09:44~10:01", "arrive_ts_left": 1659404663, "arrive_ts_right": 1659405673, "timestamp": 1659398797.9340181, "bs": "2.91b", "in_clothes": false}, "1935081": {"name": "Askeradus", "faction_id": 23952, "faction_name": "Midnight Plague", "prize": 0, "prize_on_hand": 0, "prize_total": 999999999, "arrive_time": "09:45~10:01", "arrive_ts_left": 1659404703, "arrive_ts_right": 1659405712, "timestamp": 1659398798.794027, "bs": "2.5m ~ 3.83m", "in_clothes": false}, "2220265": {"name": "SaintLuke", "faction_id": 7652, "faction_name": "Rogue Nurses", "prize": 0, "prize_on_hand": 0, "prize_total": 30002600, "arrive_time": "09:45~10:01", "arrive_ts_left": 1659404727, "arrive_ts_right": 1659405710, "timestamp": 1659398799.6384702, "bs": "1.76b", "in_clothes": true}}}, "Japan": {"raw_dict1": {"2660504": {"name": "shifjo", "faction_id": 11872, "faction_name": "Leafy&#039;s Tree", "prize": 0, "prize_on_hand": 0, "prize_total": 0, "arrive_time": "07:46~07:48", "arrive_ts_left": 1659397613, "arrive_ts_right": 1659397695, "bs": "-"}}, "raw_dict2": {"2746284": {"name": "Elfredom", "faction_id": 8152, "faction_name": "The Unwoke", "prize": 0, "prize_on_hand": 0, "prize_total": 81649400, "timestamp": 1659388604.4932876, "bs": "133.05k", "in_clothes": false}, "2432932": {"name": "SilentTears_", "faction_id": 8273, "faction_name": "Pandamonium", "prize": 0, "prize_on_hand": 0, "prize_total": 35010003, "timestamp": 1659397563.7149692, "bs": "244.62k", "in_clothes": false}, "2740516": {"name": "Sitri_", "faction_id": 478, "faction_name": "PT-Penguins", "prize": 0, "prize_on_hand": 0, "prize_total": 261090000, "timestamp": 1659398830.0030527, "bs": "787.97k ~ 2.0m", "in_clothes": false}}, "raw_dict3": {"2573449": {"name": "crazygamer7477", "faction_id": 21239, "faction_name": "Hacienda", "prize": 0, "prize_on_hand": 0, "prize_total": 200516059, "arrive_time": "08:36~08:53", "arrive_ts_left": 1659400611, "arrive_ts_right": 1659401636, "timestamp": 1659392409.3245056, "bs": "2.5m ~ 16.35m"}, "2544817": {"name": "Zappa154", "faction_id": 8085, "faction_name": "Nuclear Blast", "prize": 0, "prize_on_hand": 0, "prize_total": 25000000, "arrive_time": "09:20~09:36", "arrive_ts_left": 1659403254, "arrive_ts_right": 1659404195, "timestamp": 1659394747.0291395, "bs": "446.41m", "in_clothes": false}, "761145": {"name": "Wiffle", "faction_id": 231, "faction_name": "Destructive Anomaly", "prize": 56397250, "prize_on_hand": 0, "prize_total": 56562250, "arrive_time": "09:41~09:58", "arrive_ts_left": 1659404517, "arrive_ts_right": 1659405522, "timestamp": 1659396299.5465364, "bs": "11.45b"}, "2746266": {"name": "Sif", "faction_id": 15151, "faction_name": "The ZOO", "prize": 0, "prize_on_hand": 0, "prize_total": 2500000000, "arrive_time": "10:03~10:19", "arrive_ts_left": 1659405833, "arrive_ts_right": 1659406798, "timestamp": 1659397562.059352, "bs": "25.0k ~ 481.3k"}, "2686038": {"name": "ClaytonBigsby", "faction_id": 8510, "faction_name": "Ara Pacis", "prize": 0, "prize_on_hand": 1663677, "prize_total": 21670347, "arrive_time": "10:04~10:20", "arrive_ts_left": 1659405867, "arrive_ts_right": 1659406845, "timestamp": 1659397564.5730126, "bs": "3.29m", "in_clothes": false}}}, "Mexico": {"raw_dict1": {}, "raw_dict2": {"89242": {"name": "PappaScan", "faction_id": 8397, "faction_name": "ilimitada", "prize": 2000000, "prize_on_hand": 0, "prize_total": 27020000, "timestamp": 1659389842.0796635, "bs": "354.12m", "in_clothes": false}}, "raw_dict3": {"344271": {"name": "JASP3R", "faction_id": 8062, "faction_name": "Stygian: Awakening", "prize": 0, "prize_on_hand": 0, "prize_total": 2757250000, "arrive_time": "08:27~08:43", "arrive_ts_left": 1659400079, "arrive_ts_right": 1659400998, "timestamp": 1659400084.7150402, "bs": "2.88b", "in_clothes": false}}}, "Cayman Islands": {"raw_dict1": {}, "raw_dict2": {"2275975": {"name": "bob1066", "faction_id": 16634, "faction_name": "7th St. Assassins", "prize": 0, "prize_on_hand": 0, "prize_total": 38049998, "timestamp": 1659375712.4605172, "bs": "489.53k ~ 2.0m", "in_clothes": false}, "1625406": {"name": "Tomkins", "faction_id": 38668, "faction_name": "Valhalla - Barna", "prize": 0, "prize_on_hand": 0, "prize_total": 51496000, "timestamp": 1659385980.04755, "bs": "256.57m", "in_clothes": false}}, "raw_dict3": {}}, "Canada": {"raw_dict1": {}, "raw_dict2": {"2281305": {"name": "DeviliSnowhere", "faction_id": 8989, "faction_name": "JUX HQ", "prize": 0, "prize_on_hand": 0, "prize_total": 145000000, "timestamp": 1659390883.768666, "bs": "1.6b", "in_clothes": false}, "2676391": {"name": "Crimson_Rayne", "faction_id": 45835, "faction_name": "Fallen Angels Syndicate", "prize": 0, "prize_on_hand": 0, "prize_total": 10000000000, "timestamp": 1659390888.0334926, "bs": "250.0k ~ 2.02m", "in_clothes": false}}, "raw_dict3": {}}}